{"frames": {

"bridge_horizontal_1.png":
{
	"frame": {"x":0,"y":0,"w":16,"h":16},
	"rotated": false,
	"trimmed": false,
	"spriteSourceSize": {"x":0,"y":0,"w":16,"h":16},
	"sourceSize": {"w":16,"h":16},
	"pivot": {"x":0.5,"y":0.5}
},
"bridge_horizontal_2.png":
{
	"frame": {"x":16,"y":0,"w":16,"h":16},
	"rotated": false,
	"trimmed": false,
	"spriteSourceSize": {"x":0,"y":0,"w":16,"h":16},
	"sourceSize": {"w":16,"h":16},
	"pivot": {"x":0.5,"y":0.5}
},
"bridge_vertical_1.png":
{
	"frame": {"x":32,"y":0,"w":16,"h":16},
	"rotated": false,
	"trimmed": false,
	"spriteSourceSize": {"x":0,"y":0,"w":16,"h":16},
	"sourceSize": {"w":16,"h":16},
	"pivot": {"x":0.5,"y":0.5}
},
"bridge_vertical_2.png":
{
	"frame": {"x":48,"y":0,"w":16,"h":16},
	"rotated": false,
	"trimmed": false,
	"spriteSourceSize": {"x":0,"y":0,"w":16,"h":16},
	"sourceSize": {"w":16,"h":16},
	"pivot": {"x":0.5,"y":0.5}
},
"door_horizontal_closed.png":
{
	"frame": {"x":64,"y":0,"w":16,"h":16},
	"rotated": false,
	"trimmed": false,
	"spriteSourceSize": {"x":0,"y":0,"w":16,"h":16},
	"sourceSize": {"w":16,"h":16},
	"pivot": {"x":0.5,"y":0.5}
},
"door_horizontal_open.png":
{
	"frame": {"x":80,"y":0,"w":16,"h":16},
	"rotated": false,
	"trimmed": false,
	"spriteSourceSize": {"x":0,"y":0,"w":16,"h":16},
	"sourceSize": {"w":16,"h":16},
	"pivot": {"x":0.5,"y":0.5}
},
"door_vertical_closed.png":
{
	"frame": {"x":96,"y":0,"w":16,"h":16},
	"rotated": false,
	"trimmed": false,
	"spriteSourceSize": {"x":0,"y":0,"w":16,"h":16},
	"sourceSize": {"w":16,"h":16},
	"pivot": {"x":0.5,"y":0.5}
},
"door_vertical_open.png":
{
	"frame": {"x":112,"y":0,"w":16,"h":16},
	"rotated": false,
	"trimmed": false,
	"spriteSourceSize": {"x":0,"y":0,"w":16,"h":16},
	"sourceSize": {"w":16,"h":16},
	"pivot": {"x":0.5,"y":0.5}
},
"floor_1.png":
{
	"frame": {"x":128,"y":0,"w":16,"h":16},
	"rotated": false,
	"trimmed": false,
	"spriteSourceSize": {"x":0,"y":0,"w":16,"h":16},
	"sourceSize": {"w":16,"h":16},
	"pivot": {"x":0.5,"y":0.5}
},
"floor_2.png":
{
	"frame": {"x":144,"y":0,"w":16,"h":16},
	"rotated": false,
	"trimmed": false,
	"spriteSourceSize": {"x":0,"y":0,"w":16,"h":16},
	"sourceSize": {"w":16,"h":16},
	"pivot": {"x":0.5,"y":0.5}
},
"floor_3.png":
{
	"frame": {"x":160,"y":0,"w":16,"h":16},
	"rotated": false,
	"trimmed": false,
	"spriteSourceSize": {"x":0,"y":0,"w":16,"h":16},
	"sourceSize": {"w":16,"h":16},
	"pivot": {"x":0.5,"y":0.5}
},
"floor_4.png":
{
	"frame": {"x":176,"y":0,"w":16,"h":16},
	"rotated": false,
	"trimmed": false,
	"spriteSourceSize": {"x":0,"y":0,"w":16,"h":16},
	"sourceSize": {"w":16,"h":16},
	"pivot": {"x":0.5,"y":0.5}
},
"pillar_both_1.png":
{
	"frame": {"x":192,"y":0,"w":16,"h":16},
	"rotated": false,
	"trimmed": false,
	"spriteSourceSize": {"x":0,"y":0,"w":16,"h":16},
	"sourceSize": {"w":16,"h":16},
	"pivot": {"x":0.5,"y":0.5}
},
"pillar_both_2.png":
{
	"frame": {"x":192,"y":0,"w":16,"h":16},
	"rotated": false,
	"trimmed": false,
	"spriteSourceSize": {"x":0,"y":0,"w":16,"h":16},
	"sourceSize": {"w":16,"h":16},
	"pivot": {"x":0.5,"y":0.5}
},
"pillar_left_1.png":
{
	"frame": {"x":208,"y":0,"w":16,"h":16},
	"rotated": false,
	"trimmed": false,
	"spriteSourceSize": {"x":0,"y":0,"w":16,"h":16},
	"sourceSize": {"w":16,"h":16},
	"pivot": {"x":0.5,"y":0.5}
},
"pillar_left_2.png":
{
	"frame": {"x":224,"y":0,"w":16,"h":16},
	"rotated": false,
	"trimmed": false,
	"spriteSourceSize": {"x":0,"y":0,"w":16,"h":16},
	"sourceSize": {"w":16,"h":16},
	"pivot": {"x":0.5,"y":0.5}
},
"pillar_right_1.png":
{
	"frame": {"x":0,"y":16,"w":16,"h":16},
	"rotated": false,
	"trimmed": false,
	"spriteSourceSize": {"x":0,"y":0,"w":16,"h":16},
	"sourceSize": {"w":16,"h":16},
	"pivot": {"x":0.5,"y":0.5}
},
"pillar_right_2.png":
{
	"frame": {"x":16,"y":16,"w":16,"h":16},
	"rotated": false,
	"trimmed": false,
	"spriteSourceSize": {"x":0,"y":0,"w":16,"h":16},
	"sourceSize": {"w":16,"h":16},
	"pivot": {"x":0.5,"y":0.5}
},
"stairs_down.png":
{
	"frame": {"x":32,"y":16,"w":16,"h":16},
	"rotated": false,
	"trimmed": false,
	"spriteSourceSize": {"x":0,"y":0,"w":16,"h":16},
	"sourceSize": {"w":16,"h":16},
	"pivot": {"x":0.5,"y":0.5}
},
"stairs_up.png":
{
	"frame": {"x":48,"y":16,"w":16,"h":16},
	"rotated": false,
	"trimmed": false,
	"spriteSourceSize": {"x":0,"y":0,"w":16,"h":16},
	"sourceSize": {"w":16,"h":16},
	"pivot": {"x":0.5,"y":0.5}
},
"void.png":
{
	"frame": {"x":64,"y":16,"w":16,"h":16},
	"rotated": false,
	"trimmed": false,
	"spriteSourceSize": {"x":0,"y":0,"w":16,"h":16},
	"sourceSize": {"w":16,"h":16},
	"pivot": {"x":0.5,"y":0.5}
},
"void_cliff_1.png":
{
	"frame": {"x":80,"y":16,"w":16,"h":16},
	"rotated": false,
	"trimmed": false,
	"spriteSourceSize": {"x":0,"y":0,"w":16,"h":16},
	"sourceSize": {"w":16,"h":16},
	"pivot": {"x":0.5,"y":0.5}
},
"void_cliff_2.png":
{
	"frame": {"x":96,"y":16,"w":16,"h":16},
	"rotated": false,
	"trimmed": false,
	"spriteSourceSize": {"x":0,"y":0,"w":16,"h":16},
	"sourceSize": {"w":16,"h":16},
	"pivot": {"x":0.5,"y":0.5}
},
"wall_1.png":
{
	"frame": {"x":112,"y":16,"w":16,"h":16},
	"rotated": false,
	"trimmed": false,
	"spriteSourceSize": {"x":0,"y":0,"w":16,"h":16},
	"sourceSize": {"w":16,"h":16},
	"pivot": {"x":0.5,"y":0.5}
},
"wall_2.png":
{
	"frame": {"x":128,"y":16,"w":16,"h":16},
	"rotated": false,
	"trimmed": false,
	"spriteSourceSize": {"x":0,"y":0,"w":16,"h":16},
	"sourceSize": {"w":16,"h":16},
	"pivot": {"x":0.5,"y":0.5}
},
"wall_continue_left_corner_1.png":
{
	"frame": {"x":144,"y":16,"w":16,"h":16},
	"rotated": false,
	"trimmed": false,
	"spriteSourceSize": {"x":0,"y":0,"w":16,"h":16},
	"sourceSize": {"w":16,"h":16},
	"pivot": {"x":0.5,"y":0.5}
},
"wall_continue_left_corner_2.png":
{
	"frame": {"x":144,"y":16,"w":16,"h":16},
	"rotated": false,
	"trimmed": false,
	"spriteSourceSize": {"x":0,"y":0,"w":16,"h":16},
	"sourceSize": {"w":16,"h":16},
	"pivot": {"x":0.5,"y":0.5}
},
"wall_continue_left_corner_right_1.png":
{
	"frame": {"x":160,"y":16,"w":16,"h":16},
	"rotated": false,
	"trimmed": false,
	"spriteSourceSize": {"x":0,"y":0,"w":16,"h":16},
	"sourceSize": {"w":16,"h":16},
	"pivot": {"x":0.5,"y":0.5}
},
"wall_continue_left_corner_right_2.png":
{
	"frame": {"x":160,"y":16,"w":16,"h":16},
	"rotated": false,
	"trimmed": false,
	"spriteSourceSize": {"x":0,"y":0,"w":16,"h":16},
	"sourceSize": {"w":16,"h":16},
	"pivot": {"x":0.5,"y":0.5}
},
"wall_continue_left_corner_right_right_1.png":
{
	"frame": {"x":176,"y":16,"w":16,"h":16},
	"rotated": false,
	"trimmed": false,
	"spriteSourceSize": {"x":0,"y":0,"w":16,"h":16},
	"sourceSize": {"w":16,"h":16},
	"pivot": {"x":0.5,"y":0.5}
},
"wall_continue_left_corner_right_right_2.png":
{
	"frame": {"x":176,"y":16,"w":16,"h":16},
	"rotated": false,
	"trimmed": false,
	"spriteSourceSize": {"x":0,"y":0,"w":16,"h":16},
	"sourceSize": {"w":16,"h":16},
	"pivot": {"x":0.5,"y":0.5}
},
"wall_continue_right_corner_1.png":
{
	"frame": {"x":192,"y":16,"w":16,"h":16},
	"rotated": false,
	"trimmed": false,
	"spriteSourceSize": {"x":0,"y":0,"w":16,"h":16},
	"sourceSize": {"w":16,"h":16},
	"pivot": {"x":0.5,"y":0.5}
},
"wall_continue_right_corner_2.png":
{
	"frame": {"x":192,"y":16,"w":16,"h":16},
	"rotated": false,
	"trimmed": false,
	"spriteSourceSize": {"x":0,"y":0,"w":16,"h":16},
	"sourceSize": {"w":16,"h":16},
	"pivot": {"x":0.5,"y":0.5}
},
"wall_continue_right_corner_left_1.png":
{
	"frame": {"x":208,"y":16,"w":16,"h":16},
	"rotated": false,
	"trimmed": false,
	"spriteSourceSize": {"x":0,"y":0,"w":16,"h":16},
	"sourceSize": {"w":16,"h":16},
	"pivot": {"x":0.5,"y":0.5}
},
"wall_continue_right_corner_left_2.png":
{
	"frame": {"x":224,"y":16,"w":16,"h":16},
	"rotated": false,
	"trimmed": false,
	"spriteSourceSize": {"x":0,"y":0,"w":16,"h":16},
	"sourceSize": {"w":16,"h":16},
	"pivot": {"x":0.5,"y":0.5}
},
"wall_corner_both_1.png":
{
	"frame": {"x":0,"y":32,"w":16,"h":16},
	"rotated": false,
	"trimmed": false,
	"spriteSourceSize": {"x":0,"y":0,"w":16,"h":16},
	"sourceSize": {"w":16,"h":16},
	"pivot": {"x":0.5,"y":0.5}
},
"wall_corner_both_2.png":
{
	"frame": {"x":16,"y":32,"w":16,"h":16},
	"rotated": false,
	"trimmed": false,
	"spriteSourceSize": {"x":0,"y":0,"w":16,"h":16},
	"sourceSize": {"w":16,"h":16},
	"pivot": {"x":0.5,"y":0.5}
},
"wall_corner_left_1.png":
{
	"frame": {"x":32,"y":32,"w":16,"h":16},
	"rotated": false,
	"trimmed": false,
	"spriteSourceSize": {"x":0,"y":0,"w":16,"h":16},
	"sourceSize": {"w":16,"h":16},
	"pivot": {"x":0.5,"y":0.5}
},
"wall_corner_left_2.png":
{
	"frame": {"x":48,"y":32,"w":16,"h":16},
	"rotated": false,
	"trimmed": false,
	"spriteSourceSize": {"x":0,"y":0,"w":16,"h":16},
	"sourceSize": {"w":16,"h":16},
	"pivot": {"x":0.5,"y":0.5}
},
"wall_corner_left_down_1.png":
{
	"frame": {"x":64,"y":32,"w":16,"h":16},
	"rotated": false,
	"trimmed": false,
	"spriteSourceSize": {"x":0,"y":0,"w":16,"h":16},
	"sourceSize": {"w":16,"h":16},
	"pivot": {"x":0.5,"y":0.5}
},
"wall_corner_left_down_2.png":
{
	"frame": {"x":80,"y":32,"w":16,"h":16},
	"rotated": false,
	"trimmed": false,
	"spriteSourceSize": {"x":0,"y":0,"w":16,"h":16},
	"sourceSize": {"w":16,"h":16},
	"pivot": {"x":0.5,"y":0.5}
},
"wall_corner_left_down_corner_right_1.png":
{
	"frame": {"x":96,"y":32,"w":16,"h":16},
	"rotated": false,
	"trimmed": false,
	"spriteSourceSize": {"x":0,"y":0,"w":16,"h":16},
	"sourceSize": {"w":16,"h":16},
	"pivot": {"x":0.5,"y":0.5}
},
"wall_corner_left_down_corner_right_2.png":
{
	"frame": {"x":112,"y":32,"w":16,"h":16},
	"rotated": false,
	"trimmed": false,
	"spriteSourceSize": {"x":0,"y":0,"w":16,"h":16},
	"sourceSize": {"w":16,"h":16},
	"pivot": {"x":0.5,"y":0.5}
},
"wall_corner_right_1.png":
{
	"frame": {"x":128,"y":32,"w":16,"h":16},
	"rotated": false,
	"trimmed": false,
	"spriteSourceSize": {"x":0,"y":0,"w":16,"h":16},
	"sourceSize": {"w":16,"h":16},
	"pivot": {"x":0.5,"y":0.5}
},
"wall_corner_right_2.png":
{
	"frame": {"x":144,"y":32,"w":16,"h":16},
	"rotated": false,
	"trimmed": false,
	"spriteSourceSize": {"x":0,"y":0,"w":16,"h":16},
	"sourceSize": {"w":16,"h":16},
	"pivot": {"x":0.5,"y":0.5}
},
"wall_corner_right_corner_left_1.png":
{
	"frame": {"x":160,"y":32,"w":16,"h":16},
	"rotated": false,
	"trimmed": false,
	"spriteSourceSize": {"x":0,"y":0,"w":16,"h":16},
	"sourceSize": {"w":16,"h":16},
	"pivot": {"x":0.5,"y":0.5}
},
"wall_corner_right_corner_left_2.png":
{
	"frame": {"x":160,"y":32,"w":16,"h":16},
	"rotated": false,
	"trimmed": false,
	"spriteSourceSize": {"x":0,"y":0,"w":16,"h":16},
	"sourceSize": {"w":16,"h":16},
	"pivot": {"x":0.5,"y":0.5}
},
"wall_corner_right_corner_left_up_1.png":
{
	"frame": {"x":176,"y":32,"w":16,"h":16},
	"rotated": false,
	"trimmed": false,
	"spriteSourceSize": {"x":0,"y":0,"w":16,"h":16},
	"sourceSize": {"w":16,"h":16},
	"pivot": {"x":0.5,"y":0.5}
},
"wall_corner_right_corner_left_up_2.png":
{
	"frame": {"x":192,"y":32,"w":16,"h":16},
	"rotated": false,
	"trimmed": false,
	"spriteSourceSize": {"x":0,"y":0,"w":16,"h":16},
	"sourceSize": {"w":16,"h":16},
	"pivot": {"x":0.5,"y":0.5}
},
"wall_corner_right_down_1.png":
{
	"frame": {"x":208,"y":32,"w":16,"h":16},
	"rotated": false,
	"trimmed": false,
	"spriteSourceSize": {"x":0,"y":0,"w":16,"h":16},
	"sourceSize": {"w":16,"h":16},
	"pivot": {"x":0.5,"y":0.5}
},
"wall_corner_right_down_2.png":
{
	"frame": {"x":224,"y":32,"w":16,"h":16},
	"rotated": false,
	"trimmed": false,
	"spriteSourceSize": {"x":0,"y":0,"w":16,"h":16},
	"sourceSize": {"w":16,"h":16},
	"pivot": {"x":0.5,"y":0.5}
},
"wall_left_continue_1.png":
{
	"frame": {"x":0,"y":48,"w":16,"h":16},
	"rotated": false,
	"trimmed": false,
	"spriteSourceSize": {"x":0,"y":0,"w":16,"h":16},
	"sourceSize": {"w":16,"h":16},
	"pivot": {"x":0.5,"y":0.5}
},
"wall_left_continue_2.png":
{
	"frame": {"x":0,"y":48,"w":16,"h":16},
	"rotated": false,
	"trimmed": false,
	"spriteSourceSize": {"x":0,"y":0,"w":16,"h":16},
	"sourceSize": {"w":16,"h":16},
	"pivot": {"x":0.5,"y":0.5}
},
"wall_pillar_left_1.png":
{
	"frame": {"x":16,"y":48,"w":16,"h":16},
	"rotated": false,
	"trimmed": false,
	"spriteSourceSize": {"x":0,"y":0,"w":16,"h":16},
	"sourceSize": {"w":16,"h":16},
	"pivot": {"x":0.5,"y":0.5}
},
"wall_pillar_left_2.png":
{
	"frame": {"x":32,"y":48,"w":16,"h":16},
	"rotated": false,
	"trimmed": false,
	"spriteSourceSize": {"x":0,"y":0,"w":16,"h":16},
	"sourceSize": {"w":16,"h":16},
	"pivot": {"x":0.5,"y":0.5}
},
"wall_right_continue_1.png":
{
	"frame": {"x":48,"y":48,"w":16,"h":16},
	"rotated": false,
	"trimmed": false,
	"spriteSourceSize": {"x":0,"y":0,"w":16,"h":16},
	"sourceSize": {"w":16,"h":16},
	"pivot": {"x":0.5,"y":0.5}
},
"wall_right_continue_2.png":
{
	"frame": {"x":48,"y":48,"w":16,"h":16},
	"rotated": false,
	"trimmed": false,
	"spriteSourceSize": {"x":0,"y":0,"w":16,"h":16},
	"sourceSize": {"w":16,"h":16},
	"pivot": {"x":0.5,"y":0.5}
},
"wall_single_1.png":
{
	"frame": {"x":64,"y":48,"w":16,"h":16},
	"rotated": false,
	"trimmed": false,
	"spriteSourceSize": {"x":0,"y":0,"w":16,"h":16},
	"sourceSize": {"w":16,"h":16},
	"pivot": {"x":0.5,"y":0.5}
},
"wall_single_2.png":
{
	"frame": {"x":80,"y":48,"w":16,"h":16},
	"rotated": false,
	"trimmed": false,
	"spriteSourceSize": {"x":0,"y":0,"w":16,"h":16},
	"sourceSize": {"w":16,"h":16},
	"pivot": {"x":0.5,"y":0.5}
},
"wall_single_alone_1.png":
{
	"frame": {"x":96,"y":48,"w":16,"h":16},
	"rotated": false,
	"trimmed": false,
	"spriteSourceSize": {"x":0,"y":0,"w":16,"h":16},
	"sourceSize": {"w":16,"h":16},
	"pivot": {"x":0.5,"y":0.5}
},
"wall_single_alone_2.png":
{
	"frame": {"x":112,"y":48,"w":16,"h":16},
	"rotated": false,
	"trimmed": false,
	"spriteSourceSize": {"x":0,"y":0,"w":16,"h":16},
	"sourceSize": {"w":16,"h":16},
	"pivot": {"x":0.5,"y":0.5}
},
"wall_top_continue_1.png":
{
	"frame": {"x":128,"y":48,"w":16,"h":16},
	"rotated": false,
	"trimmed": false,
	"spriteSourceSize": {"x":0,"y":0,"w":16,"h":16},
	"sourceSize": {"w":16,"h":16},
	"pivot": {"x":0.5,"y":0.5}
},
"wall_top_continue_2.png":
{
	"frame": {"x":144,"y":48,"w":16,"h":16},
	"rotated": false,
	"trimmed": false,
	"spriteSourceSize": {"x":0,"y":0,"w":16,"h":16},
	"sourceSize": {"w":16,"h":16},
	"pivot": {"x":0.5,"y":0.5}
},
"wall_top_end_1.png":
{
	"frame": {"x":160,"y":48,"w":16,"h":16},
	"rotated": false,
	"trimmed": false,
	"spriteSourceSize": {"x":0,"y":0,"w":16,"h":16},
	"sourceSize": {"w":16,"h":16},
	"pivot": {"x":0.5,"y":0.5}
},
"wall_top_end_2.png":
{
	"frame": {"x":176,"y":48,"w":16,"h":16},
	"rotated": false,
	"trimmed": false,
	"spriteSourceSize": {"x":0,"y":0,"w":16,"h":16},
	"sourceSize": {"w":16,"h":16},
	"pivot": {"x":0.5,"y":0.5}
}},
"meta": {
	"app": "http://www.codeandweb.com/texturepacker",
	"version": "1.0",
	"image": "dungeon.png",
	"format": "RGBA8888",
	"size": {"w":240,"h":64},
	"scale": "1",
	"smartupdate": "$TexturePacker:SmartUpdate:7387f3b517850c62b040e6d9b3991d5d:5e3c7d4859c16940cff7609cf92939d4:9c0fba27a8a0c106083a8713f6c67b32$"
}
}
